lory/__init__.py
lory-0.0.1.dist-info/WHEEL
lory-0.0.1.dist-info/LICENSE
lory-0.0.1.dist-info/METADATA
lory-0.0.1.dist-info/RECORD
